drf_shop_api/__init__.py
drf_shop_api/abstract_models.py
drf_shop_api/admin.py
drf_shop_api/apps.py
drf_shop_api/customers/__init__.py
drf_shop_api/customers/filters.py
drf_shop_api/customers/models.py
drf_shop_api/customers/serializers.py
drf_shop_api/customers/tests.py
drf_shop_api/customers/urls.py
drf_shop_api/customers/views.py
drf_shop_api/decorators.py
drf_shop_api/migrations/.gitignore
drf_shop_api/migrations/__init__.py
drf_shop_api/models.py
drf_shop_api/orders/__init__.py
drf_shop_api/orders/constants.py
drf_shop_api/orders/filters.py
drf_shop_api/orders/models.py
drf_shop_api/orders/serializers.py
drf_shop_api/orders/tests.py
drf_shop_api/orders/urls.py
drf_shop_api/orders/utils.py
drf_shop_api/orders/views.py
drf_shop_api/paginators.py
drf_shop_api/permissions.py
drf_shop_api/products/__init__.py
drf_shop_api/products/constants.py
drf_shop_api/products/filters.py
drf_shop_api/products/models.py
drf_shop_api/products/serializers.py
drf_shop_api/products/tests.py
drf_shop_api/products/urls.py
drf_shop_api/products/utils.py
drf_shop_api/products/views.py
drf_shop_api/serializers.py
drf_shop_api/tasks.py
drf_shop_api/tests.py
drf_shop_api/urls.py
drf_shop_api/utils.py
drf_shop_api/views.py
drf_shop_api-0.0.3.dist-info/WHEEL
drf_shop_api-0.0.3.dist-info/METADATA
drf_shop_api-0.0.3.dist-info/RECORD
