Metadata-Version: 2.1
Name: drf-shop-api
Version: 0.0.3
Summary: Standalone shop app, that you can add to your project
Author: Oleksandr Korol
Author-email: oleksandr.korol@coaxsoft.com
Requires-Python: >=3.11,<4.0
Classifier: Programming Language :: Python :: 3
Classifier: Programming Language :: Python :: 3.11
Requires-Dist: Django (>=4.2.1,<5.0.0)
Requires-Dist: django-filter (>=23.2,<24.0)
Requires-Dist: djangorestframework (>=3.14.0,<4.0.0)
Requires-Dist: drf-yasg (>=1.21.5,<2.0.0)
Requires-Dist: rest-framework-simplejwt (>=0.0.2,<0.0.3)
